{
  "menus": [
    {
      "id": 1,
      "name": "DM_CauHinhDVTT",
      "label": "Cấu hình dịch vụ thanh toán"
    },
    {
      "id": 2,
      "name": "DM_DonViSuDungTHDVTT",
      "label": "Đơn vị sử dụng dịch vụ thanh toán"
    },
    {
      "id": 4,
      "name": "DM_NhaCungCapDVTT",
      "label": "Nhà cung cấp dịch vụ thanh toán"
    },
    {
      "id": 5,
      "name": "DM_PhanMemTHDVTT",
      "label": "Phần mềm tích hợp dịch vụ thanh toán"
    },
    {
      "id": 6,
      "name": "NhatKySuDung",
      "label": "Nhật ký sử dụng dịch vụ thanh toán"
    }
  ],
  "tables": [
    {
      "id": "DM_CauHinhDVTT",
      "name": "DM_CauHinhDVTT",
      "label": "Cấu hình dịch vụ thanh toán",
      "item_per_page": "20",
      "item_per_page_options": [
        "10",
        "20",
        "50",
        "ALL"
      ],
      "fields": [
        {
          "name": "ID",
          "label": "ID",
          "visible": false,
          "value_type": "uniqueidentifier",
          "input_type": "NO",
          "extended_search": false,
          "search_opr": "=",
          "search_opr_2": null,
          "lookup_table": false,
          "source_table": null,
          "source_key": null,
          "source_field": null,
          "required": true,
          "max_length": 0
        },
        {
          "name": "stt",
          "label": "STT",
          "visible": true,
          "value_type": "VARCHAR",
          "input_type": "TEXT",
          "extended_search": false,
          "search_opr": "LIKE",
          "search_opr_2": null,
          "lookup_table": false,
          "source_table": null,
          "source_key": null,
          "source_field": null,
          "required": false,
          "max_length": 1
        },
        {
          "name": "NenTangTTID",
          "label": "Nền tảng thanh toán",
          "visible": true,
          "value_type": "uniqueidentifier",
          "input_type": "SELECT",
          "extended_search": true,
          "search_opr": "=",
          "search_opr_2": null,
          "lookup_table": true,
          "source_table": "DM_NenTangTT",
          "source_key": "ID",
          "source_field": "TenNenTang",
          "required": true,
          "max_length": 38
        },
        {
          "name": "MaThamSo",
          "label": "Mã tham số",
          "visible": true,
          "value_type": "nvarchar",
          "input_type": "TEXT",
          "extended_search": false,
          "search_opr": "LIKE",
          "search_opr_2": null,
          "lookup_table": false,
          "source_table": null,
          "source_key": null,
          "source_field": null,
          "required": true,
          "max_length": 500
        },
        {
          "name": "TenThamSo",
          "label": "Tên tham số",
          "visible": false,
          "value_type": "nvarchar",
          "input_type": "TEXT",
          "extended_search": false,
          "search_opr": "LIKE",
          "search_opr_2": null,
          "lookup_table": false,
          "source_table": null,
          "source_key": null,
          "source_field": null,
          "required": true,
          "max_length": 500
        },
        {
          "name": "GiaTri",
          "label": "Giá trị",
          "visible": true,
          "value_type": "nvarchar",
          "input_type": "TEXT",
          "extended_search": false,
          "search_opr": "LIKE",
          "search_opr_2": null,
          "lookup_table": false,
          "source_table": null,
          "source_key": null,
          "source_field": null,
          "required": true,
          "max_length": 500
        },
        {
          "name": "TrangThai",
          "label": "Trạng thái",
          "visible": true,
          "value_type": "bit",
          "input_type": "SELECT",
          "extended_search": true,
          "search_opr": "=",
          "search_opr_2": null,
          "lookup_table": false,
          "source_table": null,
          "source_key": null,
          "source_field": null,
          "required": true,
          "max_length": 0,
          "select_options": [
            {
              "value": 1,
              "text": "Đang sử dụng"
            },
            {
              "value": 0,
              "text": "Ngừng sử dụng"
            }
          ]
        },
        {
          "name": "NguoiTao",
          "label": "Người nhập",
          "visible": true,
          "value_type": "nvarchar",
          "input_type": "HIDDEN",
          "extended_search": false,
          "search_opr": "LIKE",
          "search_opr_2": null,
          "lookup_table": false,
          "source_table": null,
          "source_key": null,
          "source_field": null,
          "required": false,
          "max_length": 38
        },
        {
          "name": "NgayTao",
          "label": "Ngày nhập",
          "visible": true,
          "value_type": "datetime",
          "input_type": "HIDDEN",
          "extended_search": false,
          "search_opr": "=",
          "search_opr_2": null,
          "lookup_table": false,
          "source_table": null,
          "source_key": null,
          "source_field": null,
          "required": false,
          "max_length": 0
        },
        {
          "name": "NguoiSua",
          "label": "Nguoi Sua",
          "visible": false,
          "value_type": "nvarchar",
          "input_type": "HIDDEN",
          "extended_search": false,
          "search_opr": "LIKE",
          "search_opr_2": null,
          "lookup_table": false,
          "source_table": null,
          "source_key": null,
          "source_field": null,
          "required": false,
          "max_length": 38
        },
        {
          "name": "NgaySua",
          "label": "Ngay Sua",
          "visible": false,
          "value_type": "datetime",
          "input_type": "HIDDEN",
          "extended_search": false,
          "search_opr": "=",
          "search_opr_2": null,
          "lookup_table": false,
          "source_table": null,
          "source_key": null,
          "source_field": null,
          "required": false,
          "max_length": 0
        },
        {
          "name": "IsXoa",
          "label": "Is Delete",
          "visible": false,
          "value_type": "bit",
          "input_type": "CHECKBOX",
          "extended_search": false,
          "search_opr": "=",
          "search_opr_2": null,
          "lookup_table": false,
          "source_table": null,
          "source_key": null,
          "source_field": null,
          "required": false,
          "max_length": 0
        }
      ]
    },
    {
      "id": "DM_DonViSuDungTHDVTT",
      "name": "DM_DonViSuDungTHDVTT",
      "label": "Đơn vị sử dụng dịch vụ thanh toán",
      "item_per_page": "20",
      "item_per_page_options": [
        "10",
        "20",
        "50",
        "ALL"
      ],
      "fields": [
        {
          "name": "ID",
          "label": "ID",
          "visible": false,
          "value_type": "uniqueidentifier",
          "input_type": "NO",
          "extended_search": false,
          "search_opr": "=",
          "search_opr_2": null,
          "lookup_table": false,
          "source_table": null,
          "source_key": null,
          "source_field": null,
          "required": true,
          "max_length": 0
        },
        {
          "name": "stt",
          "label": "STT",
          "visible": true,
          "value_type": "VARCHAR",
          "input_type": "TEXT",
          "extended_search": false,
          "search_opr": "LIKE",
          "search_opr_2": null,
          "lookup_table": false,
          "source_table": null,
          "source_key": null,
          "source_field": null,
          "required": false,
          "max_length": 1
        },
        {
          "name": "DonViID",
          "label": "Đơn vị sử dụng dịch vụ thanh toán",
          "visible": false,
          "value_type": "uniqueidentifier",
          "input_type": "TEXT",
          "extended_search": false,
          "search_opr": "=",
          "search_opr_2": null,
          "lookup_table": false,
          "source_table": null,
          "source_key": null,
          "source_field": null,
          "required": true,
          "max_length": 38
        },
        {
          "name": "DonViTen",
          "label": "Đơn vị sử dụng dịch vụ thanh toán",
          "visible": true,
          "value_type": "nvarchar",
          "input_type": "TEXT",
          "extended_search": false,
          "search_opr": "LIKE",
          "search_opr_2": null,
          "lookup_table": false,
          "source_table": null,
          "source_key": null,
          "source_field": null,
          "required": false,
          "max_length": 0
        },
        {
          "name": "PhanMemID",
          "label": "Phần mềm",
          "visible": false,
          "value_type": "varchar",
          "input_type": "TEXT",
          "extended_search": false,
          "search_opr": "LIKE",
          "search_opr_2": null,
          "lookup_table": false,
          "source_table": null,
          "source_key": null,
          "source_field": null,
          "required": true,
          "max_length": 38
        },
        {
          "name": "PhanMenTen",
          "label": "Phần mềm",
          "visible": true,
          "value_type": "nvarchar",
          "input_type": "TEXT",
          "extended_search": false,
          "search_opr": "LIKE",
          "search_opr_2": null,
          "lookup_table": false,
          "source_table": null,
          "source_key": null,
          "source_field": null,
          "required": false,
          "max_length": 0
        },
        {
          "name": "TrangThai",
          "label": "Trạng thái",
          "visible": true,
          "value_type": "bit",
          "input_type": "SELECT",
          "extended_search": true,
          "search_opr": "=",
          "search_opr_2": null,
          "lookup_table": false,
          "source_table": null,
          "source_key": null,
          "source_field": null,
          "required": false,
          "max_length": 0,
          "select_options": [
            {
              "value": 1,
              "text": "Đang tích hợp"
            },
            {
              "value": 0,
              "text": "Không tích hợp"
            }
          ]
        },
        {
          "name": "NguoiTao",
          "label": "Người nhập",
          "visible": true,
          "value_type": "nvarchar",
          "input_type": "HIDDEN",
          "extended_search": false,
          "search_opr": "LIKE",
          "search_opr_2": null,
          "lookup_table": false,
          "source_table": null,
          "source_key": null,
          "source_field": null,
          "required": false,
          "max_length": 38
        },
        {
          "name": "NgayTao",
          "label": "Ngày nhập",
          "visible": true,
          "value_type": "datetime",
          "input_type": "HIDDEN",
          "extended_search": false,
          "search_opr": "=",
          "search_opr_2": null,
          "lookup_table": false,
          "source_table": null,
          "source_key": null,
          "source_field": null,
          "required": false,
          "max_length": 0
        },
        {
          "name": "NguoiSua",
          "label": "Nguoi Sua",
          "visible": false,
          "value_type": "nvarchar",
          "input_type": "HIDDEN",
          "extended_search": false,
          "search_opr": "LIKE",
          "search_opr_2": null,
          "lookup_table": false,
          "source_table": null,
          "source_key": null,
          "source_field": null,
          "required": false,
          "max_length": 38
        },
        {
          "name": "NgaySua",
          "label": "Ngay Sua",
          "visible": false,
          "value_type": "datetime",
          "input_type": "HIDDEN",
          "extended_search": false,
          "search_opr": "=",
          "search_opr_2": null,
          "lookup_table": false,
          "source_table": null,
          "source_key": null,
          "source_field": null,
          "required": false,
          "max_length": 0
        },
        {
          "name": "IsXoa",
          "label": "Is Delete",
          "visible": false,
          "value_type": "bit",
          "input_type": "CHECKBOX",
          "extended_search": false,
          "search_opr": "=",
          "search_opr_2": null,
          "lookup_table": false,
          "source_table": null,
          "source_key": null,
          "source_field": null,
          "required": false,
          "max_length": 0
        }
      ]
    },
    {
      "id": "DM_NhaCungCapDVTT",
      "name": "DM_NhaCungCapDVTT",
      "label": "Nhà cung cấp dịch vụ thanh toán",
      "item_per_page": "20",
      "item_per_page_options": [
        "10",
        "20",
        "50",
        "ALL"
      ],
      "fields": [
        {
          "name": "ID",
          "label": "ID",
          "visible": false,
          "value_type": "uniqueidentifier",
          "input_type": "NO",
          "extended_search": false,
          "search_opr": "=",
          "search_opr_2": null,
          "lookup_table": false,
          "source_table": null,
          "source_key": null,
          "source_field": null,
          "required": true,
          "max_length": 0
        },
        {
          "name": "stt",
          "label": "STT",
          "visible": true,
          "value_type": "VARCHAR",
          "input_type": "TEXT",
          "extended_search": false,
          "search_opr": "LIKE",
          "search_opr_2": null,
          "lookup_table": false,
          "source_table": null,
          "source_key": null,
          "source_field": null,
          "required": false,
          "max_length": 1
        },
        {
          "name": "TenNCC",
          "label": "Tên nhà cung cấp dịch vụ thanh toán",
          "visible": true,
          "value_type": "nvarchar",
          "input_type": "TEXT",
          "extended_search": false,
          "search_opr": "LIKE",
          "search_opr_2": null,
          "lookup_table": false,
          "source_table": null,
          "source_key": null,
          "source_field": null,
          "required": true,
          "max_length": 500
        },
        {
          "name": "DiaChiNCC",
          "label": "Địa chỉ Trụ sở trên Giấy phép",
          "visible": true,
          "value_type": "nvarchar",
          "input_type": "TEXT",
          "extended_search": false,
          "search_opr": "LIKE",
          "search_opr_2": null,
          "lookup_table": false,
          "source_table": null,
          "source_key": null,
          "source_field": null,
          "required": true,
          "max_length": 1000
        },
        {
          "name": "SoDT",
          "label": "Số điện thoại",
          "visible": false,
          "value_type": "nvarchar",
          "input_type": "TEXT",
          "extended_search": false,
          "search_opr": "LIKE",
          "search_opr_2": null,
          "lookup_table": false,
          "source_table": null,
          "source_key": null,
          "source_field": null,
          "required": false,
          "max_length": 20
        },
        {
          "name": "SoDTSoFax",
          "label": "Số điện thoại/ Số fax",
          "visible": true,
          "value_type": "VARCHAR",
          "input_type": "TEXT",
          "extended_search": false,
          "search_opr": "LIKE",
          "search_opr_2": null,
          "lookup_table": false,
          "source_table": null,
          "source_key": null,
          "source_field": null,
          "required": false,
          "max_length": 1
        },
        {
          "name": "DiaChiGiaoDich",
          "label": "Địa chỉ giao dịch",
          "visible": true,
          "value_type": "nvarchar",
          "input_type": "TEXT",
          "extended_search": false,
          "search_opr": "LIKE",
          "search_opr_2": null,
          "lookup_table": false,
          "source_table": null,
          "source_key": null,
          "source_field": null,
          "required": true,
          "max_length": 1000
        },
        {
          "name": "SoFax",
          "label": "Số fax",
          "visible": false,
          "value_type": "nvarchar",
          "input_type": "TEXT",
          "extended_search": false,
          "search_opr": "LIKE",
          "search_opr_2": null,
          "lookup_table": false,
          "source_table": null,
          "source_key": null,
          "source_field": null,
          "required": false,
          "max_length": 20
        },
        {
          "name": "GiayPhep",
          "label": "Giấy phép",
          "visible": true,
          "value_type": "nvarchar",
          "input_type": "TEXT",
          "extended_search": false,
          "search_opr": "LIKE",
          "search_opr_2": null,
          "lookup_table": false,
          "source_table": null,
          "source_key": null,
          "source_field": null,
          "required": false,
          "max_length": 4000
        },
        {
          "name": "TrangThai",
          "label": "Trạng thái",
          "visible": true,
          "value_type": "bit",
          "input_type": "SELECT",
          "extended_search": true,
          "search_opr": "=",
          "search_opr_2": null,
          "lookup_table": false,
          "source_table": null,
          "source_key": null,
          "source_field": null,
          "required": false,
          "max_length": 0,
          "select_options": [
            {
              "value": 1,
              "text": "Đang sử dụng"
            },
            {
              "value": 0,
              "text": "Ngừng sử dụng"
            }
          ]
        },
        {
          "name": "NguoiTao",
          "label": "Người nhập",
          "visible": true,
          "value_type": "nvarchar",
          "input_type": "HIDDEN",
          "extended_search": false,
          "search_opr": "LIKE",
          "search_opr_2": null,
          "lookup_table": false,
          "source_table": null,
          "source_key": null,
          "source_field": null,
          "required": false,
          "max_length": 38
        },
        {
          "name": "NgayTao",
          "label": "Ngày nhập",
          "visible": true,
          "value_type": "datetime",
          "input_type": "HIDDEN",
          "extended_search": false,
          "search_opr": "=",
          "search_opr_2": null,
          "lookup_table": false,
          "source_table": null,
          "source_key": null,
          "source_field": null,
          "required": false,
          "max_length": 0
        },
        {
          "name": "NguoiSua",
          "label": "Nguoi Sua",
          "visible": false,
          "value_type": "nvarchar",
          "input_type": "HIDDEN",
          "extended_search": false,
          "search_opr": "LIKE",
          "search_opr_2": null,
          "lookup_table": false,
          "source_table": null,
          "source_key": null,
          "source_field": null,
          "required": false,
          "max_length": 38
        },
        {
          "name": "NgaySua",
          "label": "Ngay Sua",
          "visible": false,
          "value_type": "datetime",
          "input_type": "HIDDEN",
          "extended_search": false,
          "search_opr": "=",
          "search_opr_2": null,
          "lookup_table": false,
          "source_table": null,
          "source_key": null,
          "source_field": null,
          "required": false,
          "max_length": 0
        },
        {
          "name": "IsXoa",
          "label": "Is Delete",
          "visible": false,
          "value_type": "bit",
          "input_type": "CHECKBOX",
          "extended_search": false,
          "search_opr": "=",
          "search_opr_2": null,
          "lookup_table": false,
          "source_table": null,
          "source_key": null,
          "source_field": null,
          "required": false,
          "max_length": 0
        }
      ]
    },
    {
      "id": "DM_PhanMemTHDVTT",
      "name": "DM_PhanMemTHDVTT",
      "label": "Phần mềm tích hợp dịch vụ thanh toán",
      "item_per_page": "20",
      "item_per_page_options": [
        "10",
        "20",
        "50",
        "ALL"
      ],
      "fields": [
        {
          "name": "ID",
          "label": "ID",
          "visible": false,
          "value_type": "uniqueidentifier",
          "input_type": "NO",
          "extended_search": false,
          "search_opr": "=",
          "search_opr_2": null,
          "lookup_table": false,
          "source_table": null,
          "source_key": null,
          "source_field": null,
          "required": true,
          "max_length": 0
        },
        {
          "name": "stt",
          "label": "STT",
          "visible": true,
          "value_type": "VARCHAR",
          "input_type": "TEXT",
          "extended_search": false,
          "search_opr": "LIKE",
          "search_opr_2": null,
          "lookup_table": false,
          "source_table": null,
          "source_key": null,
          "source_field": null,
          "required": false,
          "max_length": 1
        },
        {
          "name": "PhanMemID",
          "label": "Phần mềm tích hợp dịch vụ thanh toán",
          "visible": false,
          "value_type": "uniqueidentifier",
          "input_type": "TEXT",
          "extended_search": false,
          "search_opr": "=",
          "search_opr_2": null,
          "lookup_table": false,
          "source_table": null,
          "source_key": null,
          "source_field": null,
          "required": true,
          "max_length": 38
        },
        {
          "name": "PhanMenTen",
          "label": "Phần mềm tích hợp dịch vụ thanh toán",
          "visible": true,
          "value_type": "nvarchar",
          "input_type": "HIDDEN",
          "extended_search": false,
          "search_opr": "LIKE",
          "search_opr_2": null,
          "lookup_table": false,
          "source_table": null,
          "source_key": null,
          "source_field": null,
          "required": false,
          "max_length": 0
        },
        {
          "name": "TrangThai",
          "label": "Trạng thái",
          "visible": true,
          "value_type": "bit",
          "input_type": "SELECT",
          "extended_search": true,
          "search_opr": "=",
          "search_opr_2": null,
          "lookup_table": false,
          "source_table": null,
          "source_key": null,
          "source_field": null,
          "required": false,
          "max_length": 0,
          "select_options": [
            {
              "value": 1,
              "text": "Đang tích hợp"
            },
            {
              "value": 0,
              "text": "Không tích hợp"
            }
          ]
        },
        {
          "name": "NguoiTao",
          "label": "Người nhập",
          "visible": true,
          "value_type": "nvarchar",
          "input_type": "HIDDEN",
          "extended_search": false,
          "search_opr": "LIKE",
          "search_opr_2": null,
          "lookup_table": false,
          "source_table": null,
          "source_key": null,
          "source_field": null,
          "required": false,
          "max_length": 38
        },
        {
          "name": "NgayTao",
          "label": "Ngày nhập",
          "visible": true,
          "value_type": "datetime",
          "input_type": "HIDDEN",
          "extended_search": false,
          "search_opr": "=",
          "search_opr_2": null,
          "lookup_table": false,
          "source_table": null,
          "source_key": null,
          "source_field": null,
          "required": false,
          "max_length": 0
        },
        {
          "name": "NguoiSua",
          "label": "Nguoi Sua",
          "visible": false,
          "value_type": "nvarchar",
          "input_type": "HIDDEN",
          "extended_search": false,
          "search_opr": "LIKE",
          "search_opr_2": null,
          "lookup_table": false,
          "source_table": null,
          "source_key": null,
          "source_field": null,
          "required": false,
          "max_length": 38
        },
        {
          "name": "NgaySua",
          "label": "Ngay Sua",
          "visible": false,
          "value_type": "datetime",
          "input_type": "HIDDEN",
          "extended_search": false,
          "search_opr": "=",
          "search_opr_2": null,
          "lookup_table": false,
          "source_table": null,
          "source_key": null,
          "source_field": null,
          "required": false,
          "max_length": 0
        },
        {
          "name": "IsXoa",
          "label": "Is Delete",
          "visible": false,
          "value_type": "bit",
          "input_type": "CHECKBOX",
          "extended_search": false,
          "search_opr": "=",
          "search_opr_2": null,
          "lookup_table": false,
          "source_table": null,
          "source_key": null,
          "source_field": null,
          "required": false,
          "max_length": 0
        }
      ]
    },
    {
      "id": "NhatKySuDung",
      "name": "NhatKySuDung",
      "label": "Nhật ký sử dụng dịch vụ thanh toán",
      "item_per_page": "20",
      "item_per_page_options": [
        "10",
        "20",
        "50",
        "ALL"
      ],
      "fields": [
        {
          "name": "ID",
          "label": "ID",
          "visible": false,
          "value_type": "uniqueidentifier",
          "input_type": "NO",
          "extended_search": false,
          "search_opr": "=",
          "search_opr_2": null,
          "lookup_table": false,
          "source_table": null,
          "source_key": null,
          "source_field": null,
          "required": true,
          "max_length": 0
        },
        {
          "name": "stt",
          "label": "STT",
          "visible": true,
          "value_type": "VARCHAR",
          "input_type": "TEXT",
          "extended_search": false,
          "search_opr": "LIKE",
          "search_opr_2": null,
          "lookup_table": false,
          "source_table": null,
          "source_key": null,
          "source_field": null,
          "required": false,
          "max_length": 1
        },
        {
          "name": "NenTangID",
          "label": "Nền tảng thanh toán",
          "visible": true,
          "value_type": "uniqueidentifier",
          "input_type": "SELECT",
          "extended_search": true,
          "search_opr": "=",
          "search_opr_2": null,
          "lookup_table": true,
          "source_table": "DM_NenTangTT",
          "source_key": "ID",
          "source_field": "TenNenTang",
          "required": false,
          "max_length": 38
        },
        {
          "name": "PhanMemID",
          "label": "Phần mềm nghiệp vụ",
          "visible": false,
          "value_type": "uniqueidentifier",
          "input_type": "SELECT",
          "extended_search": true,
          "search_opr": "=",
          "search_opr_2": null,
          "lookup_table": true,
          "source_table": "DM_PhanMemTHDVTT",
          "source_key": "ID",
          "source_field": "PhanMenTen",
          "required": false,
          "max_length": 38
        },
        {
          "name": "PhanMenTen",
          "label": "Phần mềm nghiệp vụ",
          "visible": true,
          "value_type": "nvarchar",
          "input_type": "TEXT",
          "extended_search": false,
          "search_opr": "LIKE",
          "search_opr_2": null,
          "lookup_table": false,
          "source_table": null,
          "source_key": null,
          "source_field": null,
          "required": false,
          "max_length": 0
        },
        {
          "name": "DonViTT",
          "label": "Đơn vị thực hiện thanh toán",
          "visible": false,
          "value_type": "uniqueidentifier",
          "input_type": "TEXT",
          "extended_search": false,
          "search_opr": "=",
          "search_opr_2": null,
          "lookup_table": false,
          "source_table": null,
          "source_key": null,
          "source_field": null,
          "required": false,
          "max_length": 38
        },
        {
          "name": "TenDonViTT",
          "label": "Đơn vị thực hiện thanh toán",
          "visible": true,
          "value_type": "nvarchar",
          "input_type": "TEXTAREA",
          "extended_search": false,
          "search_opr": "LIKE",
          "search_opr_2": null,
          "lookup_table": false,
          "source_table": null,
          "source_key": null,
          "source_field": null,
          "required": false,
          "max_length": 0
        },
        {
          "name": "DichVuTT",
          "label": "Dịch vụ thanh toán",
          "visible": false,
          "value_type": "uniqueidentifier",
          "input_type": "TEXT",
          "extended_search": false,
          "search_opr": "=",
          "search_opr_2": null,
          "lookup_table": false,
          "source_table": null,
          "source_key": null,
          "source_field": null,
          "required": false,
          "max_length": 38
        },
        {
          "name": "TenDichVuTT",
          "label": "Dịch vụ thanh toán",
          "visible": true,
          "value_type": "nvarchar",
          "input_type": "TEXTAREA",
          "extended_search": false,
          "search_opr": "LIKE",
          "search_opr_2": null,
          "lookup_table": false,
          "source_table": null,
          "source_key": null,
          "source_field": null,
          "required": false,
          "max_length": 0
        },
        {
          "name": "TenTGTT",
          "label": "Tên TGTT",
          "visible": true,
          "value_type": "nvarchar",
          "input_type": "TEXT",
          "extended_search": false,
          "search_opr": "LIKE",
          "search_opr_2": null,
          "lookup_table": false,
          "source_table": null,
          "source_key": null,
          "source_field": null,
          "required": false,
          "max_length": 1000
        },
        {
          "name": "MaGDTGTT",
          "label": "Mã giao dịch tại TGTT",
          "visible": true,
          "value_type": "nvarchar",
          "input_type": "TEXT",
          "extended_search": false,
          "search_opr": "LIKE",
          "search_opr_2": null,
          "lookup_table": false,
          "source_table": null,
          "source_key": null,
          "source_field": null,
          "required": false,
          "max_length": 1000
        },
        {
          "name": "MaGDPayGov",
          "label": "Mã giao dịch tại PayGov",
          "visible": true,
          "value_type": "nvarchar",
          "input_type": "TEXT",
          "extended_search": false,
          "search_opr": "LIKE",
          "search_opr_2": null,
          "lookup_table": false,
          "source_table": null,
          "source_key": null,
          "source_field": null,
          "required": false,
          "max_length": 1000
        },
        {
          "name": "MaYCTTHoanTra",
          "label": "Mã yêu cầu thanh toán/ hoàn trả",
          "visible": true,
          "value_type": "nvarchar",
          "input_type": "TEXT",
          "extended_search": false,
          "search_opr": "LIKE",
          "search_opr_2": null,
          "lookup_table": false,
          "source_table": null,
          "source_key": null,
          "source_field": null,
          "required": false,
          "max_length": 1000
        },
        {
          "name": "MaHDYCTT",
          "label": "Mã hóa đơn yêu cầu thanh toán",
          "visible": true,
          "value_type": "nvarchar",
          "input_type": "TEXT",
          "extended_search": false,
          "search_opr": "LIKE",
          "search_opr_2": null,
          "lookup_table": false,
          "source_table": null,
          "source_key": null,
          "source_field": null,
          "required": false,
          "max_length": 1000
        },
        {
          "name": "SoTenTT",
          "label": "Số tiền thanh toán",
          "visible": true,
          "value_type": "decimal",
          "input_type": "TEXT",
          "extended_search": false,
          "search_opr": "=",
          "search_opr_2": null,
          "lookup_table": false,
          "source_table": null,
          "source_key": null,
          "source_field": null,
          "required": false,
          "max_length": 0
        },
        {
          "name": "ThongTinHDTT",
          "label": "Thông tin hóa đơn thanh toán",
          "visible": true,
          "value_type": "nvarchar",
          "input_type": "TEXT",
          "extended_search": false,
          "search_opr": "LIKE",
          "search_opr_2": null,
          "lookup_table": false,
          "source_table": null,
          "source_key": null,
          "source_field": null,
          "required": false,
          "max_length": 1000
        },
        {
          "name": "ThoiGianKHTT",
          "label": "Thời gian khách hàng thanh toán",
          "visible": true,
          "value_type": "datetime",
          "input_type": "TEXT",
          "extended_search": true,
          "search_opr": ">=",
          "search_opr_2": "<=",
          "lookup_table": false,
          "source_table": null,
          "source_key": null,
          "source_field": null,
          "required": false,
          "max_length": 0
        },
        {
          "name": "LoaiGD",
          "label": "Loại giao dịch",
          "visible": true,
          "value_type": "nvarchar",
          "input_type": "TEXT",
          "extended_search": false,
          "search_opr": "LIKE",
          "search_opr_2": null,
          "lookup_table": false,
          "source_table": null,
          "source_key": null,
          "source_field": null,
          "required": false,
          "max_length": 100
        },
        {
          "name": "TrangThai",
          "label": "Trạng thái",
          "visible": true,
          "value_type": "int",
          "input_type": "SELECT",
          "extended_search": true,
          "search_opr": "=",
          "search_opr_2": null,
          "lookup_table": false,
          "source_table": null,
          "source_key": null,
          "source_field": null,
          "required": false,
          "max_length": 0,
          "select_options": [
            {
              "value": 1,
              "text": "Thành công"
            },
            {
              "value": 0,
              "text": "Không thành công"
            }
          ]
        },
        {
          "name": "MoTaLyDo",
          "label": "Mô tả lý do",
          "visible": true,
          "value_type": "nvarchar",
          "input_type": "TEXT",
          "extended_search": false,
          "search_opr": "LIKE",
          "search_opr_2": null,
          "lookup_table": false,
          "source_table": null,
          "source_key": null,
          "source_field": null,
          "required": false,
          "max_length": 1000
        },
        {
          "name": "NgaySua",
          "label": "Ngay Sua",
          "visible": false,
          "value_type": "datetime",
          "input_type": "TEXT",
          "extended_search": false,
          "search_opr": "=",
          "search_opr_2": null,
          "lookup_table": false,
          "source_table": null,
          "source_key": null,
          "source_field": null,
          "required": false,
          "max_length": 0
        }
      ]
    }
  ]
}